migranats/__init__.py
migranats/__meta__.py
migranats-0.1.0.dist-info/METADATA
migranats-0.1.0.dist-info/WHEEL
migranats-0.1.0.dist-info/RECORD
