Metadata-Version: 2.3
Name: migranats
Version: 0.1.0
Summary: A tool that helps you perform migrations to Nats Jetstream
Author: sheldy
License-Expression: MIT
Classifier: Programming Language :: Python :: 3.9
Classifier: Programming Language :: Python :: 3.10
